README.md
pyproject.toml
setup.py
graphos/__init__.py
graphos.egg-info/PKG-INFO
graphos.egg-info/SOURCES.txt
graphos.egg-info/dependency_links.txt
graphos.egg-info/entry_points.txt
graphos.egg-info/requires.txt
graphos.egg-info/top_level.txt
graphos/src/__init__.py
graphos/src/constants.py
graphos/src/cursor.py
graphos/src/edge.py
graphos/src/hud.py
graphos/src/main.py
graphos/src/menu.py
graphos/src/modal.py
graphos/src/node.py
graphos/src/offset.py
graphos/src/textbox.py
graphos/src/utils.py
graphos/src/view.py