Metadata-Version: 2.4
Name: graphos
Version: 0.2.7
Summary: Terminal graph visualization tool.
Author: Edgardo Gutierrez Jr.
Author-email: edgardogutierrezjr@gmail.com
Requires-Python: >=3.10
Requires-Dist: debugpy>=1.8.14
Requires-Dist: rich>=14.0.0
Requires-Dist: setuptools>=79.0.1
Requires-Dist: twine>=6.1.0
Dynamic: author
Dynamic: author-email
Dynamic: requires-python
